{"annotator_id": "CALIML", "discharge_summary_id": "18830_135675_28929", "annotations": [{"decision": "Baby girl [**Known lastname 69778**] was a 2.3 kg product of a 36 and 2/7 weeks gestation born to a 35-year-old G3, P1, now 2 woman.", "category": "Category 3: Defining problem", "start_offset": "145", "end_offset": "277", "annotation_id": "EJ_000"}, {"decision": "Notable for depression. Not on medication.", "category": "Category 3: Defining problem", "start_offset": "302", "end_offset": "344", "annotation_id": "EJ_001"}, {"decision": "A positive, direct Coombs' negative, hepatitis surface antigen negative, RPR nonreactive, rubella immune, GBS unknown.", "category": "Category 7: Evaluating test result", "start_offset": "365", "end_offset": "483", "annotation_id": "EJ_002"}, {"decision": "Antenatal history was complicated by IUGR ", "category": "Category 3: Defining problem", "start_offset": "485", "end_offset": "527", "annotation_id": "EJ_003"}, {"decision": "underwent repeat cesarean section under spinal anesthesia", "category": "Category 6: Therapeutic procedure related", "start_offset": "541", "end_offset": "598", "annotation_id": "EJ_004"}, {"decision": "no interpartum fever", "category": "Category 3: Defining problem", "start_offset": "610", "end_offset": "630", "annotation_id": "EJ_005"}, {"decision": "Rupture of membranes occurred at delivery and yielded clear amniotic fluid", "category": "Category 3: Defining problem", "start_offset": "632", "end_offset": "706", "annotation_id": "EJ_006"}, {"decision": "did not receive interpartum antibiotic prophylaxis", "category": "Category 5: Drug related", "start_offset": "712", "end_offset": "762", "annotation_id": "EJ_007"}, {"decision": "The infant was vigorous at delivery, orally and nasally suctioned, dried", "category": "Category 3: Defining problem", "start_offset": "783", "end_offset": "855", "annotation_id": "EJ_008"}, {"decision": "Tactile stimulus", "category": "Category 3: Defining problem", "start_offset": "857", "end_offset": "873", "annotation_id": "EJ_009"}, {"decision": "Apgars were 8 at 1 minute, and 8 at 5 minutes.", "category": "Category 3: Defining problem", "start_offset": "902", "end_offset": "948", "annotation_id": "EJ_010"}, {"decision": "The infant was noted to have grunting with respirations", "category": "Category 3: Defining problem", "start_offset": "949", "end_offset": "1004", "annotation_id": "EJ_011"}, {"decision": "transferred to the newborn intensive care unit for further evaluation.", "category": "Category 1: Contact related", "start_offset": "1013", "end_offset": "1083", "annotation_id": "EJ_012"}, {"decision": "Birth weight was 2.3 kg, 25th to 50th percentile; head circumference 30.5 cm, 10th percentile; length 46.25 cm, 25th to 50th percentile. ", "category": "Category 3: Defining problem", "start_offset": "1108", "end_offset": "1245", "annotation_id": "EJ_013"}, {"decision": "Anterior fontanel soft and flat. Nondysmorphic.", "category": "Category 3: Defining problem", "start_offset": "1245", "end_offset": "1292", "annotation_id": "EJ_014"}, {"decision": "Palate intact. Neck and mouth normal. No nasal flaring.", "category": "Category 3: Defining problem", "start_offset": "1293", "end_offset": "1348", "annotation_id": "EJ_015"}, {"decision": "Red reflex normal bilaterally", "category": "Category 3: Defining problem", "start_offset": "1349", "end_offset": "1378", "annotation_id": "EJ_016"}, {"decision": "Chest with mild intercostal retractions. Good breaths sounds bilaterally. No adventitious sounds. ", "category": "Category 3: Defining problem", "start_offset": "1380", "end_offset": "1478", "annotation_id": "EJ_017"}, {"decision": "Well perfused. Regular rate and rhythm. Femoral pulses normal. S1 and S2 normal. No murmurs. ", "category": "Category 3: Defining problem", "start_offset": "1494", "end_offset": "1587", "annotation_id": "EJ_018"}, {"decision": "Soft, nondistended. No organomegaly. No masses. Bowel sounds active. Anus patent. Three vessel umbilical cord. ", "category": "Category 3: Defining problem", "start_offset": "1596", "end_offset": "1707", "annotation_id": "EJ_019"}, {"decision": "Normal external female genitalia. ", "category": "Category 3: Defining problem", "start_offset": "1722", "end_offset": "1756", "annotation_id": "EJ_020"}, {"decision": "The infant is active, responding to stimuli. Tone mildly decreased in symmetrical distribution", "category": "Category 3: Defining problem", "start_offset": "1756", "end_offset": "1850", "annotation_id": "EJ_021"}, {"decision": "Moves all extremities symmetrically. Suck, root, gag present and normal. Normal spine with limbs, hips and clavicles.", "category": "Category 3: Defining problem", "start_offset": "1852", "end_offset": "1969", "annotation_id": "EJ_022"}, {"decision": "placed on CPAP for management of respiratory distress", "category": "Category 6: Therapeutic procedure related", "start_offset": "2088", "end_offset": "2141", "annotation_id": "EJ_023"}, {"decision": "respiratory distress", "category": "Category 3: Defining problem", "start_offset": 2121, "end_offset": 2141, "annotation_id": "EJ_024"}, {"decision": "The infant transitioned to room air by day of life No. 1 and has been stable in room air since that time.", "category": "Category 3: Defining problem", "start_offset": "2143", "end_offset": "2248", "annotation_id": "EJ_025"}, {"decision": "The infant has been cardiovascularly stable with a new onset murmur ", "category": "Category 3: Defining problem", "start_offset": "2266", "end_offset": "2334", "annotation_id": "EJ_026"}, {"decision": "seen by TCH cardiology service", "category": "Category 1: Contact related", "start_offset": "2392", "end_offset": "2422", "annotation_id": "EJ_027"}, {"decision": "The cardiology service felt the murmur was consistent with a small VSD.", "category": "Category 3: Defining problem", "start_offset": "2425", "end_offset": "2496", "annotation_id": "EJ_028"}, {"decision": "60 cc per kg per day of D10W", "category": "Category 6: Therapeutic procedure related", "start_offset": "2673", "end_offset": "2701", "annotation_id": "EJ_029"}, {"decision": "The infant has been euglycemic throughout hospital course.", "category": "Category 3: Defining problem", "start_offset": "2918", "end_offset": "2976", "annotation_id": "EJ_030"}, {"decision": "phototherapy ", "category": "Category 6: Therapeutic procedure related", "start_offset": "3159", "end_offset": "3172", "annotation_id": "EJ_031"}, {"decision": "Her rebound bili after phototherapy stopped was 6.9/0.2.", "category": "Category 7: Evaluating test result", "start_offset": "3186", "end_offset": "3242", "annotation_id": "EJ_032"}, {"decision": "CBC was benign and blood cultures remained negative at 48 hours ", "category": "Category 7: Evaluating test result", "start_offset": "3408", "end_offset": "3472", "annotation_id": "EJ_033"}, {"decision": "ampicillin and gentamycin were discontinued. ", "category": "Category 5: Drug related", "start_offset": "3486", "end_offset": "3531", "annotation_id": "EJ_034"}, {"decision": "The infant has been appropriate for gestational age. ", "category": "Category 5: Drug related", "start_offset": "3544", "end_offset": "3597", "annotation_id": "EJ_035"}, {"decision": "Audiology hearing screen has been performed with automated auditory brain stem responses and the infant passed in the right ear but referred in the left ear.", "category": "Category 7: Evaluating test result", "start_offset": "3607", "end_offset": "3764", "annotation_id": "EJ_036"}, {"decision": "Stable", "category": "Category 3: Defining problem", "start_offset": "3791", "end_offset": "3797", "annotation_id": "EJ_037"}, {"decision": "NAME OF PRIMARY PEDIATRICIAN:  Dr. [**First Name4 (NamePattern1) 2951**] [**Last Name (NamePattern1) 57282**]. Telephone No.:  [**Telephone/Fax (1) 69779**].", "category": "Category 1: Contact related", "start_offset": "3834", "end_offset": "3991", "annotation_id": "EJ_038"}, {"decision": "Feeds at discharge: Continue ad lib feeding breast milk     or Similac 20 calorie", "category": "Category 9: Advice and precaution", "start_offset": "4019", "end_offset": "4100", "annotation_id": "EJ_039"}, {"decision": ".  Car seat position screening was performed.  The infant     was screened with 90-minute screening in the car seat and     the infant passed.", "category": "Category 3: Defining problem", "start_offset": "4136", "end_offset": "4278", "annotation_id": "EJ_040"}, {"decision": "State newborn screens have been sent per protocol and     have been within normal limits.", "category": "Category 3: Defining problem", "start_offset": "4283", "end_offset": "4372", "annotation_id": "EJ_041"}, {"decision": "The infant received Hep B vaccine     on [**8-30**].", "category": "Category 5: Drug related", "start_offset": "4402", "end_offset": "4454", "annotation_id": "EJ_042"}, {"decision": "Prematurity at 36 2/7 weeks gestation", "category": "Category 3: Defining problem", "start_offset": "4481", "end_offset": "4518", "annotation_id": "EJ_043"}, {"decision": "Mild respiratory distress syndrome", "category": "Category 3: Defining problem", "start_offset": "4523", "end_offset": "4557", "annotation_id": "EJ_044"}, {"decision": "Hyperbilirubinemia", "category": "Category 3: Defining problem", "start_offset": "4563", "end_offset": "4581", "annotation_id": "EJ_045"}, {"decision": "Rule out sepsis with antibiotics", "category": "Category 3: Defining problem", "start_offset": "4587", "end_offset": "4619", "annotation_id": "EJ_046"}, {"decision": "antibiotics", "category": "Category 5: Drug related", "start_offset": 4608, "end_offset": 4619, "annotation_id": "EJ_047"}]}