{
    "annotator_id": "JVAZNAR",
    "discharge_summary_id": "97842_155272_35916",
    "annotations": [
        {
            "decision": "Hypertensive emergency.",
            "category": "Category 3: Defining problem",
            "start_offset": 276,
            "end_offset": 298,
            "annotation_id": "RC_000"
        },
        {
            "decision": "history of depression and suicidal ideation",
            "category": "Category 3: Defining problem",
            "start_offset": 390,
            "end_offset": 433,
            "annotation_id": "RC_001"
        },
        {
            "decision": "anxiety",
            "category": "Category 3: Defining problem",
            "start_offset": 435,
            "end_offset": 442,
            "annotation_id": "RC_002"
        },
        {
            "decision": ", history of hyperaldosteronism",
            "category": "Category 3: Defining problem",
            "start_offset": 444,
            "end_offset": 473,
            "annotation_id": "RC_003"
        },
        {
            "decision": "poorly-controlled hypertension",
            "category": "Category 3: Defining problem",
            "start_offset": 475,
            "end_offset": 505,
            "annotation_id": "RC_004"
        },
        {
            "decision": "type A dissection ",
            "category": "Category 3: Defining problem",
            "start_offset": 507,
            "end_offset": 524,
            "annotation_id": "RC_005"
        },
        {
            "decision": "s/p emergent repair ([**11/2143**]),",
            "category": "Category 6: Therapeutic procedure related",
            "start_offset": 525,
            "end_offset": 559,
            "annotation_id": "RC_006"
        },
        {
            "decision": "type B dissection extending to iliac arteries",
            "category": "Category 3: Defining problem",
            "start_offset": 562,
            "end_offset": 607,
            "annotation_id": "RC_007"
        },
        {
            "decision": "transferred from vascular surgery service ",
            "category": "Category 1: Contact related",
            "start_offset": 613,
            "end_offset": 654,
            "annotation_id": "RC_008"
        },
        {
            "decision": "malignant hypertension.",
            "category": "Category 3: Defining problem",
            "start_offset": 681,
            "end_offset": 703,
            "annotation_id": "RC_009"
        },
        {
            "decision": "scheduled for an elective fenestration of his type B dissection and possible left renal artery stenting on [**4-14**]. ",
            "category": "Category 6: Therapeutic procedure related",
            "start_offset": 784,
            "end_offset": 901,
            "annotation_id": "RC_010"
        },
        {
            "decision": "elevated BP in the 220s",
            "category": "Category 7: Evaluating test result",
            "start_offset": 974,
            "end_offset": 997,
            "annotation_id": "RC_011"
        },
        {
            "decision": "SI ",
            "category": "Category 3: Defining problem",
            "start_offset": 1106,
            "end_offset": 1108,
            "annotation_id": "RC_012"
        },
        {
            "decision": "malignant hypertension.",
            "category": "Category 3: Defining problem",
            "start_offset": 1138,
            "end_offset": 1160,
            "annotation_id": "RC_013"
        },
        {
            "decision": "admitted to the cardiovascular ICU",
            "category": "Category 1: Contact related",
            "start_offset": 1169,
            "end_offset": 1203,
            "annotation_id": "RC_014"
        },
        {
            "decision": "hypokalemia (2.6",
            "category": "Category 7: Evaluating test result",
            "start_offset": 1384,
            "end_offset": 1400,
            "annotation_id": "RC_015"
        },
        {
            "decision": "was on ACEi, BB at that time, but not on an aldosterone antagonist. ",
            "category": "Category 5: Drug related",
            "start_offset": 1564,
            "end_offset": 1630,
            "annotation_id": "RC_016"
        },
        {
            "decision": "undergone imaging which showed a 13mm myolipoma in the right adrenal in [**2140**] and [**2142**], but no adenoma.",
            "category": "Category 3: Defining problem",
            "start_offset": 1644,
            "end_offset": 1757,
            "annotation_id": "RC_017"
        },
        {
            "decision": "emergent type A dissection repair",
            "category": "Category 6: Therapeutic procedure related",
            "start_offset": 1838,
            "end_offset": 1871,
            "annotation_id": "RC_018"
        },
        {
            "decision": "noted again to be hypokalemic and hypertensive ",
            "category": "Category 3: Defining problem",
            "start_offset": 1903,
            "end_offset": 1949,
            "annotation_id": "RC_019"
        },
        {
            "decision": "requiring a labetalol drip. ",
            "category": "Category 5: Drug related",
            "start_offset": 1950,
            "end_offset": 1976,
            "annotation_id": "RC_020"
        },
        {
            "decision": "secondary hypertension ",
            "category": "Category 3: Defining problem",
            "start_offset": 2017,
            "end_offset": 2039,
            "annotation_id": "RC_021"
        },
        {
            "decision": "discharged on a regimen of amlodipine",
            "category": "Category 5: Drug related",
            "start_offset": 2163,
            "end_offset": 2200,
            "annotation_id": "RC_022"
        },
        {
            "decision": "labetalol,",
            "category": "Category 5: Drug related",
            "start_offset": 2202,
            "end_offset": 2211,
            "annotation_id": "RC_023"
        },
        {
            "decision": "hydralazine,",
            "category": "Category 5: Drug related",
            "start_offset": 2213,
            "end_offset": 2224,
            "annotation_id": "RC_024"
        },
        {
            "decision": "lisinopril",
            "category": "Category 5: Drug related",
            "start_offset": 2226,
            "end_offset": 2236,
            "annotation_id": "RC_025"
        },
        {
            "decision": "HCTZ, ",
            "category": "Category 5: Drug related",
            "start_offset": 2238,
            "end_offset": 2242,
            "annotation_id": "RC_026"
        },
        {
            "decision": "clonidine patch",
            "category": "Category 5: Drug related",
            "start_offset": 2244,
            "end_offset": 2259,
            "annotation_id": "RC_027"
        },
        {
            "decision": "and spironolactone.",
            "category": "Category 5: Drug related",
            "start_offset": 2261,
            "end_offset": 2279,
            "annotation_id": "RC_028"
        },
        {
            "decision": "followed by CT surgery ",
            "category": "Category 1: Contact related",
            "start_offset": 2302,
            "end_offset": 2324,
            "annotation_id": "RC_029"
        },
        {
            "decision": " with serial CT scans. His initial post-op showed a 17 mm myolipoma in the right adrenal gland and a type B dissection extending from SCL to internal/external iliacs. ",
            "category": "Category 3: Defining problem",
            "start_offset": 2325,
            "end_offset": 2489,
            "annotation_id": "RC_030"
        },
        {
            "decision": "Subsequent scans on [**2143-11-28**], [**2143-12-25**], [**2144-3-25**], [**2144-4-15**] have shown no change in the appearance of the right adrenal mass but have shown new left renal and left renal wedge infarcts. ",
            "category": "Category 3: Defining problem",
            "start_offset": 2491,
            "end_offset": 2704,
            "annotation_id": "RC_031"
        },
        {
            "decision": "It also appears that the left renal artery communicates with both true and false lumens with a flap noted. ",
            "category": "Category 7: Evaluating test result",
            "start_offset": 2706,
            "end_offset": 2811,
            "annotation_id": "RC_032"
        },
        {
            "decision": " His most recent scan shows a stable lipoma (-70 houndsfield units).",
            "category": "Category 3: Defining problem",
            "start_offset": 2813,
            "end_offset": 2878,
            "annotation_id": "RC_033"
        },
        {
            "decision": "Type A aortic dissection ",
            "category": "Category 3: Defining problem",
            "start_offset": 3262,
            "end_offset": 3286,
            "annotation_id": "RC_034"
        },
        {
            "decision": "s/p emergent repair ([**11/2143**])",
            "category": "Category 6: Therapeutic procedure related",
            "start_offset": 3287,
            "end_offset": 3321,
            "annotation_id": "RC_035"
        },
        {
            "decision": "Type B aortic dissection (SCL->ext/int iliacs; all major vessels originate from true lumen, left RA originates from both)",
            "category": "Category 3: Defining problem",
            "start_offset": 3323,
            "end_offset": 3443,
            "annotation_id": "RC_036"
        },
        {
            "decision": "Hypertension",
            "category": "Category 3: Defining problem",
            "start_offset": 3445,
            "end_offset": 3457,
            "annotation_id": "RC_037"
        },
        {
            "decision": "Hyperlipidemia",
            "category": "Category 3: Defining problem",
            "start_offset": 3458,
            "end_offset": 3472,
            "annotation_id": "RC_038"
        },
        {
            "decision": "Prior abdominal surgery s/p mesenteric biopsies",
            "category": "Category 6: Therapeutic procedure related",
            "start_offset": 3473,
            "end_offset": 3520,
            "annotation_id": "RC_039"
        },
        {
            "decision": "Adrenal myolipoma",
            "category": "Category 3: Defining problem",
            "start_offset": 3521,
            "end_offset": 3538,
            "annotation_id": "RC_040"
        },
        {
            "decision": "Depression",
            "category": "Category 3: Defining problem",
            "start_offset": 3539,
            "end_offset": 3549,
            "annotation_id": "RC_041"
        },
        {
            "decision": "History of suicidal ideation",
            "category": "Category 3: Defining problem",
            "start_offset": 3550,
            "end_offset": 3578,
            "annotation_id": "RC_042"
        },
        {
            "decision": "General: Middle Aged, slightly depressed affect, NAD",
            "category": "Category 3: Defining problem",
            "start_offset": 4101,
            "end_offset": 4153,
            "annotation_id": "RC_043"
        },
        {
            "decision": "HEENT: PERRL, EOMI, no scleral icterus noted.",
            "category": "Category 3: Defining problem",
            "start_offset": 4154,
            "end_offset": 4198,
            "annotation_id": "RC_044"
        },
        {
            "decision": "Neck: No thyromegaly noted, no buffalo hump",
            "category": "Category 3: Defining problem",
            "start_offset": 4200,
            "end_offset": 4243,
            "annotation_id": "RC_045"
        },
        {
            "decision": "Chest: Lungs CTA bilaterally, no wheezes, ronchi or rales. No gynecomastia",
            "category": "Category 3: Defining problem",
            "start_offset": 4244,
            "end_offset": 4318,
            "annotation_id": "RC_046"
        },
        {
            "decision": "Cardiac: RR, S1 S2, 2/6 systolic @ LUSB",
            "category": "Category 3: Defining problem",
            "start_offset": 4319,
            "end_offset": 4358,
            "annotation_id": "RC_047"
        },
        {
            "decision": "Abdomen: Non-tender, non-distended, normoactive bowel sounds, no striae",
            "category": "Category 3: Defining problem",
            "start_offset": 4359,
            "end_offset": 4430,
            "annotation_id": "RC_048"
        },
        {
            "decision": "Extremities: No edema, 2+ DP pulses b/l, warm to touch",
            "category": "Category 3: Defining problem",
            "start_offset": 4432,
            "end_offset": 4486,
            "annotation_id": "RC_049"
        },
        {
            "decision": "Skin: numerous well healed surgical scars",
            "category": "Category 3: Defining problem",
            "start_offset": 4487,
            "end_offset": 4528,
            "annotation_id": "RC_050"
        },
        {
            "decision": "Neurologic: Alert, oriented to hospital, [**2143**], person. CN II-XII intact",
            "category": "Category 3: Defining problem",
            "start_offset": 4529,
            "end_offset": 4606,
            "annotation_id": "RC_051"
        },
        {
            "decision": "Strength: [**4-14**] upper and lower bilaterally",
            "category": "Category 3: Defining problem",
            "start_offset": 4607,
            "end_offset": 4655,
            "annotation_id": "RC_052"
        },
        {
            "decision": "Sensation: decreased sensation to light touch in R lateral thigh and foot, but pinprick intact bilaterally",
            "category": "Category 3: Defining problem",
            "start_offset": 4656,
            "end_offset": 4762,
            "annotation_id": "RC_053"
        },
        {
            "decision": "CT HEAD W/O CONTRAST ([**2144-4-13**]): FINDINGS: There is no intracranial hemorrhage, mass effect or vascular territorial infarction. ",
            "category": "Category 3: Defining problem",
            "start_offset": 4792,
            "end_offset": 4925,
            "annotation_id": "RC_054"
        },
        {
            "decision": "Ventricles are normal in size and in configuration.",
            "category": "Category 7: Evaluating test result",
            "start_offset": 4927,
            "end_offset": 4977,
            "annotation_id": "RC_055"
        },
        {
            "decision": "Grey-white matter differentiation is slightly indistinct globally. ",
            "category": "Category 7: Evaluating test result",
            "start_offset": 4979,
            "end_offset": 5044,
            "annotation_id": "RC_056"
        },
        {
            "decision": " In addition, minimal sulcal effacement is noted diffusely. This latter finding is most prominent near the vertex. ",
            "category": "Category 7: Evaluating test result",
            "start_offset": 5046,
            "end_offset": 5158,
            "annotation_id": "RC_057"
        },
        {
            "decision": "The basilar cisterns are unremarkable",
            "category": "Category 7: Evaluating test result",
            "start_offset": 5160,
            "end_offset": 5197,
            "annotation_id": "RC_058"
        },
        {
            "decision": "Slight caudal position of the cerebellar tonsils thus most likely represents incidental tonsillar ectopia",
            "category": "Category 7: Evaluating test result",
            "start_offset": 5199,
            "end_offset": 5304,
            "annotation_id": "RC_059"
        },
        {
            "decision": "tonsillar ectopia",
            "category": "Category 3: Defining problem",
            "start_offset": 5287,
            "end_offset": 5304,
            "annotation_id": "RC_060"
        },
        {
            "decision": "Extracranial soft tissue structures are unremarkable.",
            "category": "Category 7: Evaluating test result",
            "start_offset": 5306,
            "end_offset": 5358,
            "annotation_id": "RC_061"
        },
        {
            "decision": "Visualized osseous structures, paranasal sinuses and mastoid air cells are clear",
            "category": "Category 7: Evaluating test result",
            "start_offset": 5360,
            "end_offset": 5440,
            "annotation_id": "RC_062"
        },
        {
            "decision": "1. Subtle loss of grey-white matter differentiation with minimal sulcal effacement, particularly at the vertex, raising the possibility of early cerebral edema, in this context. There is no specific evidence of PRES.",
            "category": "Category 3: Defining problem",
            "start_offset": 5454,
            "end_offset": 5669,
            "annotation_id": "RC_063"
        },
        {
            "decision": "2. Low-lying cerebellar tonsils, unlikely to be related to #1, above; this may represent coincidental tonsillar ectopia.",
            "category": "Category 3: Defining problem",
            "start_offset": 5671,
            "end_offset": 5790,
            "annotation_id": "RC_064"
        },
        {
            "decision": "CXR PORTABLE ([**2144-4-13**]): IMPRESSION: Stable cardiomegaly ",
            "category": "Category 3: Defining problem",
            "start_offset": 5793,
            "end_offset": 5856,
            "annotation_id": "RC_065"
        },
        {
            "decision": "and prominence of the aortic arch, unchanged compared to prior study of [**2143-11-27**]. Although there is no change in the mediastinal contours, complications related to prior aortic dissection and repair cannot be excluded ",
            "category": "Category 7: Evaluating test result",
            "start_offset": 5857,
            "end_offset": 6082,
            "annotation_id": "RC_066"
        },
        {
            "decision": "a CT of the chest should be obtained if there is clinical concern for such complications.",
            "category": "Category 2: Gathering additional information",
            "start_offset": 6087,
            "end_offset": 6175,
            "annotation_id": "RC_067"
        },
        {
            "decision": "[**4-15**] CT ABD: CT OF THE ABDOMEN WITH AND WITHOUT IV CONTRAST: There is a right adrenal lesion measuring 1.8 cm x 1.7 cm, which is predominantly fatty in attenuation, with internal Hounsfield units of approximately -70 [**Doctor Last Name **]. ",
            "category": "Category 7: Evaluating test result",
            "start_offset": 6178,
            "end_offset": 6424,
            "annotation_id": "RC_068"
        },
        {
            "decision": "These findings are most compatible with a myelolipoma, and has not significantly changed from the prior study. ",
            "category": "Category 7: Evaluating test result",
            "start_offset": 6426,
            "end_offset": 6535,
            "annotation_id": "RC_069"
        },
        {
            "decision": "These findings are most compatible with a myelolipoma, and has not significantly changed from the prior study. ",
            "category": "Category 3: Defining problem",
            "start_offset": 6426,
            "end_offset": 6535,
            "annotation_id": "RC_070"
        },
        {
            "decision": "Immediately superior to this myelolipoma, there is a slight fullness of the right adrenal gland which is within the range of normal, without evidence of a discrete nodule",
            "category": "Category 7: Evaluating test result",
            "start_offset": 6537,
            "end_offset": 6707,
            "annotation_id": "RC_071"
        },
        {
            "decision": ". A nonspecific punctate focus of calcification is seen.",
            "category": "Category 7: Evaluating test result",
            "start_offset": 6709,
            "end_offset": 6762,
            "annotation_id": "RC_072"
        },
        {
            "decision": "The right adrenal gland is otherwise unremarkable.",
            "category": "Category 7: Evaluating test result",
            "start_offset": 6764,
            "end_offset": 6813,
            "annotation_id": "RC_073"
        },
        {
            "decision": ". Similarly, the left adrenal gland is slightly prominent in appearance",
            "category": "Category 7: Evaluating test result",
            "start_offset": 6815,
            "end_offset": 6884,
            "annotation_id": "RC_074"
        },
        {
            "decision": ". However, there is no evidence to support adrenal hyperplasia or a discrete nodule, and is within normal limits",
            "category": "Category 7: Evaluating test result",
            "start_offset": 6886,
            "end_offset": 6996,
            "annotation_id": "RC_075"
        },
        {
            "decision": ". Within the visualized lung bases, there is minimal dependent atelectases.",
            "category": "Category 3: Defining problem",
            "start_offset": 6998,
            "end_offset": 7070,
            "annotation_id": "RC_076"
        },
        {
            "decision": "Again seen is a dissection of the aorta, with the dissection flap extending into the left renal artery. ",
            "category": "Category 3: Defining problem",
            "start_offset": 7072,
            "end_offset": 7174,
            "annotation_id": "RC_077"
        },
        {
            "decision": "These findings were better assessed on dedicated CTA [**2144-3-25**]. ",
            "category": "Category 7: Evaluating test result",
            "start_offset": 7176,
            "end_offset": 7244,
            "annotation_id": "RC_078"
        },
        {
            "decision": "The visualized liver, gallbladder, spleen, and pancreas are unremarkable. ",
            "category": "Category 7: Evaluating test result",
            "start_offset": 7246,
            "end_offset": 7318,
            "annotation_id": "RC_079"
        },
        {
            "decision": "renal infarct",
            "category": "Category 3: Defining problem",
            "start_offset": 7432,
            "end_offset": 7445,
            "annotation_id": "RC_080"
        },
        {
            "decision": "Within the left kidney, there are peripheral, wedge-shaped areas of low attenuation, which may reflect areas of renal infarct.",
            "category": "Category 7: Evaluating test result",
            "start_offset": 7320,
            "end_offset": 7445,
            "annotation_id": "RC_081"
        },
        {
            "decision": "Previously noted suspicious area for infarct within the right kidney is not imaged on this study",
            "category": "Category 7: Evaluating test result",
            "start_offset": 7447,
            "end_offset": 7543,
            "annotation_id": "RC_082"
        },
        {
            "decision": "No free fluid or pathologic adenopathy is identified",
            "category": "Category 7: Evaluating test result",
            "start_offset": 7545,
            "end_offset": 7597,
            "annotation_id": "RC_083"
        },
        {
            "decision": "There is a \"[**Doctor First Name 9189**]\" appearance of the mesentery, which is unchanged. ",
            "category": "Category 7: Evaluating test result",
            "start_offset": 7599,
            "end_offset": 7688,
            "annotation_id": "RC_084"
        },
        {
            "decision": "Visualized osseous structures reveal no suspicious sclerotic or lytic lesion.",
            "category": "Category 7: Evaluating test result",
            "start_offset": 7690,
            "end_offset": 7766,
            "annotation_id": "RC_085"
        },
        {
            "decision": "1. Stable right adrenal myelolipoma",
            "category": "Category 3: Defining problem",
            "start_offset": 7780,
            "end_offset": 7815,
            "annotation_id": "RC_086"
        },
        {
            "decision": "Otherwise, the remainder of the adrenal glands are within normal limits, without evidence for an additional nodule or hyperplasia",
            "category": "Category 7: Evaluating test result",
            "start_offset": 7817,
            "end_offset": 7946,
            "annotation_id": "RC_087"
        },
        {
            "decision": "2. Aortic dissection, with dissection flap extending into the left renal artery, and probable areas of left renal infarct.",
            "category": "Category 3: Defining problem",
            "start_offset": 7948,
            "end_offset": 8069,
            "annotation_id": "RC_088"
        },
        {
            "decision": "3. Stable \"[**Doctor First Name 9189**]\" mesenteric appearance. ",
            "category": "Category 7: Evaluating test result",
            "start_offset": 8141,
            "end_offset": 8203,
            "annotation_id": "RC_089"
        },
        {
            "decision": "history of malignant hypertension",
            "category": "Category 3: Defining problem",
            "start_offset": 8246,
            "end_offset": 8279,
            "annotation_id": "RC_090"
        },
        {
            "decision": "type A aortic dissection ",
            "category": "Category 3: Defining problem",
            "start_offset": 8281,
            "end_offset": 8305,
            "annotation_id": "RC_091"
        },
        {
            "decision": "s/p emergent repair in [**11/2143**], ",
            "category": "Category 6: Therapeutic procedure related",
            "start_offset": 8306,
            "end_offset": 8342,
            "annotation_id": "RC_092"
        },
        {
            "decision": "type B dissection",
            "category": "Category 3: Defining problem",
            "start_offset": 8344,
            "end_offset": 8361,
            "annotation_id": "RC_093"
        },
        {
            "decision": "and depression ",
            "category": "Category 3: Defining problem",
            "start_offset": 8363,
            "end_offset": 8377,
            "annotation_id": "RC_094"
        },
        {
            "decision": "hypertensive emergency requiring ICU stay.",
            "category": "Category 3: Defining problem",
            "start_offset": 8391,
            "end_offset": 8432,
            "annotation_id": "RC_095"
        },
        {
            "decision": "# Malignant hypertension",
            "category": "Category 3: Defining problem",
            "start_offset": 8437,
            "end_offset": 8459,
            "annotation_id": "RC_096"
        },
        {
            "decision": "with accompanying lethargy",
            "category": "Category 3: Defining problem",
            "start_offset": 8522,
            "end_offset": 8548,
            "annotation_id": "RC_097"
        },
        {
            "decision": "taken to the cardiovascular ICU on admission",
            "category": "Category 1: Contact related",
            "start_offset": 8557,
            "end_offset": 8601,
            "annotation_id": "RC_098"
        },
        {
            "decision": "started on nitro and labetalol drip.",
            "category": "Category 5: Drug related",
            "start_offset": 8616,
            "end_offset": 8651,
            "annotation_id": "RC_099"
        },
        {
            "decision": "switched to oral labetalol",
            "category": "Category 5: Drug related",
            "start_offset": 8662,
            "end_offset": 8688,
            "annotation_id": "RC_100"
        },
        {
            "decision": "HCTZ-triamterene",
            "category": "Category 5: Drug related",
            "start_offset": 8690,
            "end_offset": 8706,
            "annotation_id": "RC_101"
        },
        {
            "decision": "clonidine patch",
            "category": "Category 5: Drug related",
            "start_offset": 8708,
            "end_offset": 8723,
            "annotation_id": "RC_102"
        },
        {
            "decision": "lisinopril,",
            "category": "Category 5: Drug related",
            "start_offset": 8725,
            "end_offset": 8735,
            "annotation_id": "RC_103"
        },
        {
            "decision": "and hydralazine",
            "category": "Category 5: Drug related",
            "start_offset": 8737,
            "end_offset": 8752,
            "annotation_id": "RC_104"
        },
        {
            "decision": "meds were than adjusted to target a systolic blood pressure of 130-150",
            "category": "Category 4: Treatment goal",
            "start_offset": 8754,
            "end_offset": 8824,
            "annotation_id": "RC_105"
        },
        {
            "decision": "which has been recommended by the vascular surgery service.",
            "category": "Category 1: Contact related",
            "start_offset": 8826,
            "end_offset": 8884,
            "annotation_id": "RC_106"
        },
        {
            "decision": "Endocrinology was consulted ",
            "category": "Category 2: Gathering additional information",
            "start_offset": 8886,
            "end_offset": 8913,
            "annotation_id": "RC_107"
        },
        {
            "decision": "regarding the history of hyperaldosteronism.",
            "category": "Category 3: Defining problem",
            "start_offset": 8914,
            "end_offset": 8957,
            "annotation_id": "RC_108"
        },
        {
            "decision": "he was started on aldosterone antagonist therapy first with spironolactone then eplerenone to avoid gynecomastia",
            "category": "Category 5: Drug related",
            "start_offset": 8975,
            "end_offset": 9087,
            "annotation_id": "RC_109"
        },
        {
            "decision": "antihypertensive regimen consists of clonidine patch, labetalol, eplerenone, and amlodipine at the doses listed later in the report. ",
            "category": "Category 5: Drug related",
            "start_offset": 9115,
            "end_offset": 9246,
            "annotation_id": "RC_110"
        },
        {
            "decision": "stable electrolytes ",
            "category": "Category 7: Evaluating test result",
            "start_offset": 9308,
            "end_offset": 9327,
            "annotation_id": "RC_111"
        },
        {
            "decision": "If BP meds are to be readjusted, consideration could be given to decreasing the frequency of the labetalol from tid to [**Hospital1 **] dosing to simplify his regimen.",
            "category": "Category 5: Drug related",
            "start_offset": 9351,
            "end_offset": 9517,
            "annotation_id": "RC_112"
        },
        {
            "decision": "# Depression:",
            "category": "Category 3: Defining problem",
            "start_offset": 9522,
            "end_offset": 9532,
            "annotation_id": "RC_113"
        },
        {
            "decision": "Psychiatry was consulted in the emergency room when patient appeared depressed and endorsed suicidal ideation. ",
            "category": "Category 2: Gathering additional information",
            "start_offset": 9534,
            "end_offset": 9643,
            "annotation_id": "RC_114"
        },
        {
            "decision": "He was started on a clonazepam, risperidone, and citalopram per their recommendations. ",
            "category": "Category 5: Drug related",
            "start_offset": 9645,
            "end_offset": 9730,
            "annotation_id": "RC_115"
        },
        {
            "decision": "has follow-up scheduled with his previous therapist and psychiatrist for the upcoming month. ",
            "category": "Category 1: Contact related",
            "start_offset": 9778,
            "end_offset": 9869,
            "annotation_id": "RC_116"
        },
        {
            "decision": "# Question of primary hyperaldosteronism",
            "category": "Category 3: Defining problem",
            "start_offset": 9874,
            "end_offset": 9912,
            "annotation_id": "RC_117"
        },
        {
            "decision": "refractory hypertension and hypokalemia ",
            "category": "Category 3: Defining problem",
            "start_offset": 9918,
            "end_offset": 9957,
            "annotation_id": "RC_118"
        },
        {
            "decision": " prompted endocrine consult ",
            "category": "Category 2: Gathering additional information",
            "start_offset": 9958,
            "end_offset": 9984,
            "annotation_id": "RC_119"
        },
        {
            "decision": "On CT, there was a right adrenal lesion measuring 1.8 cm x 1.7 cm compatible with myelolipoma, with slight fullness of the right adrenal gland within the range of normal. There was no evidence of adenoma",
            "category": "Category 3: Defining problem",
            "start_offset": 9998,
            "end_offset": 10201,
            "annotation_id": "RC_120"
        },
        {
            "decision": "Aldosterone and renin levels were sent",
            "category": "Category 2: Gathering additional information",
            "start_offset": 10203,
            "end_offset": 10241,
            "annotation_id": "RC_121"
        },
        {
            "decision": "on spironolactone at the time the labs were drawn.",
            "category": "Category 5: Drug related",
            "start_offset": 10313,
            "end_offset": 10362,
            "annotation_id": "RC_122"
        },
        {
            "decision": "It is believed that he has primary hyperaldosteronism. There may be a secretory adrenal adenoma not picked up on imaging or it is possible, given his family history of premature hypertension, that he has glucocorticoid remedial hyperaldosteronism",
            "category": "Category 3: Defining problem",
            "start_offset": 10364,
            "end_offset": 10610,
            "annotation_id": "RC_123"
        },
        {
            "decision": "glucocorticoid remedial hyperaldosteronism.",
            "category": "Category 3: Defining problem",
            "start_offset": 10568,
            "end_offset": 10610,
            "annotation_id": "RC_124"
        },
        {
            "decision": "continue on eplerenone for the time being",
            "category": "Category 5: Drug related",
            "start_offset": 10620,
            "end_offset": 10661,
            "annotation_id": "RC_125"
        },
        {
            "decision": "and will follow-up in endocrine clinic at [**Hospital1 18**] in early",
            "category": "Category 1: Contact related",
            "start_offset": 10663,
            "end_offset": 10732,
            "annotation_id": "RC_126"
        },
        {
            "decision": "and will follow-up in endocrine clinic at [**Hospital1 18**] in early [**Month (only) **].",
            "category": "Category 1: Contact related",
            "start_offset": 10663,
            "end_offset": 10752,
            "annotation_id": "RC_127"
        },
        {
            "decision": "# Left renal infarct: Likely in the setting of aortic dissection",
            "category": "Category 3: Defining problem",
            "start_offset": 10757,
            "end_offset": 10819,
            "annotation_id": "RC_128"
        },
        {
            "decision": "Vascular surgery did not feel endovascular intervention was necessary and recommended blood pressure control as above.",
            "category": "Category 1: Contact related",
            "start_offset": 10892,
            "end_offset": 11009,
            "annotation_id": "RC_129"
        },
        {
            "decision": " Type B aortic dissection",
            "category": "Category 3: Defining problem",
            "start_offset": 11014,
            "end_offset": 11038,
            "annotation_id": "RC_130"
        },
        {
            "decision": "On CT scan, there was evidence of aortic dissection, with dissection flap extending into the left renal artery, and probable areas of left renal infarct",
            "category": "Category 3: Defining problem",
            "start_offset": 11040,
            "end_offset": 11192,
            "annotation_id": "RC_131"
        },
        {
            "decision": "Vascular service deferred surgical intervention, ",
            "category": "Category 8: Deferment",
            "start_offset": 11194,
            "end_offset": 11241,
            "annotation_id": "RC_132"
        },
        {
            "decision": "target SBP 130-150",
            "category": "Category 4: Treatment goal",
            "start_offset": 11285,
            "end_offset": 11303,
            "annotation_id": "RC_133"
        },
        {
            "decision": "follow-up in vascular clinic later this month",
            "category": "Category 1: Contact related",
            "start_offset": 11343,
            "end_offset": 11388,
            "annotation_id": "RC_134"
        },
        {
            "decision": "Catopress 0.3mg qSunday (Rx due [**2144-3-20**])",
            "category": "Category 5: Drug related",
            "start_offset": 11490,
            "end_offset": 11537,
            "annotation_id": "RC_135"
        },
        {
            "decision": "Lisinopril 40mg [**Hospital1 **] (last picked up [**2-/2144**])",
            "category": "Category 5: Drug related",
            "start_offset": 11539,
            "end_offset": 11601,
            "annotation_id": "RC_136"
        },
        {
            "decision": "Pravastatin 20mg daily",
            "category": "Category 5: Drug related",
            "start_offset": 11603,
            "end_offset": 11625,
            "annotation_id": "RC_137"
        },
        {
            "decision": "Labetalol 1200mg [**Hospital1 **]",
            "category": "Category 5: Drug related",
            "start_offset": 11626,
            "end_offset": 11659,
            "annotation_id": "RC_138"
        },
        {
            "decision": "Terazosin 10mg at bedtime (last picked up [**2-/2144**])",
            "category": "Category 5: Drug related",
            "start_offset": 11660,
            "end_offset": 11715,
            "annotation_id": "RC_139"
        },
        {
            "decision": "Amlodipine (Rx due [**2144-3-20**])",
            "category": "Category 5: Drug related",
            "start_offset": 11717,
            "end_offset": 11751,
            "annotation_id": "RC_140"
        },
        {
            "decision": "Triamterene-HCTZ 37.5mg/25mg daily (Rx due [**2144-3-20**])",
            "category": "Category 5: Drug related",
            "start_offset": 11753,
            "end_offset": 11811,
            "annotation_id": "RC_141"
        },
        {
            "decision": "Amlodipine 75mg q6hrs (last picked up [**2-/2144**])",
            "category": "Category 5: Drug related",
            "start_offset": 11813,
            "end_offset": 11864,
            "annotation_id": "RC_142"
        },
        {
            "decision": "FeSO4 325mg daily",
            "category": "Category 5: Drug related",
            "start_offset": 11866,
            "end_offset": 11883,
            "annotation_id": "RC_143"
        },
        {
            "decision": "Colace 100mg [**Hospital1 **]",
            "category": "Category 5: Drug related",
            "start_offset": 11884,
            "end_offset": 11913,
            "annotation_id": "RC_144"
        },
        {
            "decision": "ASA 81mg daily",
            "category": "Category 5: Drug related",
            "start_offset": 11914,
            "end_offset": 11928,
            "annotation_id": "RC_145"
        },
        {
            "decision": "Ranitidine 150mg [**Hospital1 **] (last picked up [**2-/2144**])",
            "category": "Category 5: Drug related",
            "start_offset": 11929,
            "end_offset": 11992,
            "annotation_id": "RC_146"
        },
        {
            "decision": "Zolpidem 10mg at bedtime (Rx due [**2144-3-20**])",
            "category": "Category 5: Drug related",
            "start_offset": 11994,
            "end_offset": 12042,
            "annotation_id": "RC_147"
        },
        {
            "decision": "1. Amlodipine 10 mg Tablet Sig: One (1) Tablet PO once a day. Disp:*30 Tablet(s)* Refills:*2*",
            "category": "Category 5: Drug related",
            "start_offset": 12068,
            "end_offset": 12161,
            "annotation_id": "RC_148"
        },
        {
            "decision": "2. Eplerenone 50 mg Tablet Sig: One (1) Tablet PO once a day. Disp:*30 Tablet(s)* Refills:*2*",
            "category": "Category 5: Drug related",
            "start_offset": 12162,
            "end_offset": 12255,
            "annotation_id": "RC_149"
        },
        {
            "decision": "3. Labetalol 300 mg Tablet Sig: Two (2) Tablet PO three times a day. Disp:*180 Tablet(s)* Refills:*2*",
            "category": "Category 5: Drug related",
            "start_offset": 12256,
            "end_offset": 12357,
            "annotation_id": "RC_150"
        },
        {
            "decision": "4. Clonidine 0.3 mg/24 hr Patch Weekly Sig: One (1)  Transdermal QWED. Disp:*4 qs* Refills:*2*",
            "category": "Category 5: Drug related",
            "start_offset": 12358,
            "end_offset": 12452,
            "annotation_id": "RC_151"
        },
        {
            "decision": "5. Blood Pressure Kit     Kit Sig: One (1)  Miscellaneous twice a day. Disp:*1 qs* Refills:*0*",
            "category": "Category 5: Drug related",
            "start_offset": 12453,
            "end_offset": 12547,
            "annotation_id": "RC_152"
        },
        {
            "decision": "6. Citalopram 20 mg Tablet Sig: One (1) Tablet PO DAILY (Daily). Disp:*30 Tablet(s)* Refills:*2*",
            "category": "Category 5: Drug related",
            "start_offset": 12548,
            "end_offset": 12644,
            "annotation_id": "RC_153"
        },
        {
            "decision": "7. Clonazepam 0.5 mg Tablet Sig: One (1) Tablet PO twice a day:",
            "category": "Category 5: Drug related",
            "start_offset": 12645,
            "end_offset": 12707,
            "annotation_id": "RC_154"
        },
        {
            "decision": "Do not drive after taking this medicine. This medicine will cause you to be sleepy. Disp:*60 Tablet(s)* Refills:*1*",
            "category": "Category 9: Advice and precaution",
            "start_offset": 12709,
            "end_offset": 12824,
            "annotation_id": "RC_155"
        },
        {
            "decision": "8. Risperidone 1 mg Tablet Sig: One (1) Tablet PO at bedtime:",
            "category": "Category 5: Drug related",
            "start_offset": 12825,
            "end_offset": 12885,
            "annotation_id": "RC_156"
        },
        {
            "decision": "This medicine should be taken at night. It may make you drowsy. Disp:*30 Tablet(s)* Refills:*1*",
            "category": "Category 9: Advice and precaution",
            "start_offset": 12887,
            "end_offset": 12982,
            "annotation_id": "RC_157"
        },
        {
            "decision": "9. Pravastatin 20 mg Tablet Sig: One (1) Tablet PO at bedtime. Disp:*30 Tablet(s)* Refills:*2",
            "category": "Category 5: Drug related",
            "start_offset": 12983,
            "end_offset": 13076,
            "annotation_id": "RC_158"
        },
        {
            "decision": "Please have labs drawn qweekly for chem 7 and faxed to Dr. [**First Name8 (NamePattern2) **] [**Name (STitle) **] at [**Telephone/Fax (1) 3541**].",
            "category": "Category 9: Advice and precaution",
            "start_offset": 13102,
            "end_offset": 13247,
            "annotation_id": "RC_159"
        },
        {
            "decision": "Hypertensive emergency",
            "category": "Category 3: Defining problem",
            "start_offset": 13376,
            "end_offset": 13398,
            "annotation_id": "RC_160"
        },
        {
            "decision": "Type B aortic dissection",
            "category": "Category 3: Defining problem",
            "start_offset": 13399,
            "end_offset": 13423,
            "annotation_id": "RC_161"
        },
        {
            "decision": "Depression .",
            "category": "Category 3: Defining problem",
            "start_offset": 13424,
            "end_offset": 13434,
            "annotation_id": "RC_162"
        },
        {
            "decision": "Hyperlipidemia",
            "category": "Category 3: Defining problem",
            "start_offset": 13458,
            "end_offset": 13472,
            "annotation_id": "RC_163"
        },
        {
            "decision": "History of suicidal ideation",
            "category": "Category 3: Defining problem",
            "start_offset": 13473,
            "end_offset": 13501,
            "annotation_id": "RC_164"
        },
        {
            "decision": "Discharge Condition: Vital signs stable. Blood pressure controlled with systolic blood pressure 130-140s.",
            "category": "Category 3: Defining problem",
            "start_offset": 13504,
            "end_offset": 13608,
            "annotation_id": "RC_165"
        },
        {
            "decision": "very high blood pressure",
            "category": "Category 7: Evaluating test result",
            "start_offset": 13674,
            "end_offset": 13698,
            "annotation_id": "RC_166"
        },
        {
            "decision": "(hypertensive emergency) and damage to a blood vessel in the chest (aortic dissection). ",
            "category": "Category 3: Defining problem",
            "start_offset": 13700,
            "end_offset": 13784,
            "annotation_id": "RC_167"
        },
        {
            "decision": "Your blood pressure medicines were changed",
            "category": "Category 5: Drug related",
            "start_offset": 13816,
            "end_offset": 13858,
            "annotation_id": "RC_168"
        },
        {
            "decision": "Your goal blood pressure after discharge, for the time being, should be 130-150/70-80.",
            "category": "Category 4: Treatment goal",
            "start_offset": 13860,
            "end_offset": 13945,
            "annotation_id": "RC_169"
        },
        {
            "decision": "You were also evaluated by psychiatry ",
            "category": "Category 1: Contact related",
            "start_offset": 13949,
            "end_offset": 13986,
            "annotation_id": "RC_170"
        },
        {
            "decision": "for depression and anxiety",
            "category": "Category 3: Defining problem",
            "start_offset": 13987,
            "end_offset": 14013,
            "annotation_id": "RC_171"
        },
        {
            "decision": "They have recommended that you take citalopram, clonazepam and risperidone",
            "category": "Category 5: Drug related",
            "start_offset": 14015,
            "end_offset": 14089,
            "annotation_id": "RC_172"
        },
        {
            "decision": "-amlodipine 10 mg once daily for blood pressure",
            "category": "Category 5: Drug related",
            "start_offset": 14207,
            "end_offset": 14254,
            "annotation_id": "RC_173"
        },
        {
            "decision": "-eplerenone 50 mg once daily for blood pressure",
            "category": "Category 5: Drug related",
            "start_offset": 14255,
            "end_offset": 14302,
            "annotation_id": "RC_174"
        },
        {
            "decision": "-labetalol 600 mg three times daily for blood pressure",
            "category": "Category 5: Drug related",
            "start_offset": 14303,
            "end_offset": 14357,
            "annotation_id": "RC_175"
        },
        {
            "decision": "-clonidine patch 0.3 mg to be changed every week for blood pressure",
            "category": "Category 5: Drug related",
            "start_offset": 14358,
            "end_offset": 14425,
            "annotation_id": "RC_176"
        },
        {
            "decision": "-citalopram 20 mg once daily for depression and anxiety",
            "category": "Category 5: Drug related",
            "start_offset": 14426,
            "end_offset": 14481,
            "annotation_id": "RC_177"
        },
        {
            "decision": "depression and anxiety",
            "category": "Category 3: Defining problem",
            "start_offset": 14459,
            "end_offset": 14481,
            "annotation_id": "RC_178"
        },
        {
            "decision": "-clonazepam 0.5 mg twice daily for anxiety",
            "category": "Category 5: Drug related",
            "start_offset": 14482,
            "end_offset": 14524,
            "annotation_id": "RC_179"
        },
        {
            "decision": "anxiety",
            "category": "Category 3: Defining problem",
            "start_offset": 14517,
            "end_offset": 14524,
            "annotation_id": "RC_180"
        },
        {
            "decision": "-risperidone 1 mg once daily at night for anxiety",
            "category": "Category 5: Drug related",
            "start_offset": 14525,
            "end_offset": 14574,
            "annotation_id": "RC_181"
        },
        {
            "decision": "anxiety",
            "category": "Category 3: Defining problem",
            "start_offset": 14567,
            "end_offset": 14574,
            "annotation_id": "RC_182"
        },
        {
            "decision": "-pravastatin 20 mg once daily at night for high cholesterol",
            "category": "Category 5: Drug related",
            "start_offset": 14575,
            "end_offset": 14634,
            "annotation_id": "RC_183"
        },
        {
            "decision": "high cholesterol",
            "category": "Category 7: Evaluating test result",
            "start_offset": 14618,
            "end_offset": 14634,
            "annotation_id": "RC_184"
        },
        {
            "decision": "-terazosin 10 mg once daily at night",
            "category": "Category 5: Drug related",
            "start_offset": 14635,
            "end_offset": 14671,
            "annotation_id": "RC_185"
        },
        {
            "decision": "Please call your doctor or return to the emergency room if you experience any back or chest pain, changes in vision, headache, or any other new concerning symptoms",
            "category": "Category 9: Advice and precaution",
            "start_offset": 14736,
            "end_offset": 14899,
            "annotation_id": "RC_186"
        },
        {
            "decision": "It is imperative that you follow a low-salt diet (no more McDonald's), ",
            "category": "Category 9: Advice and precaution",
            "start_offset": 14903,
            "end_offset": 14971,
            "annotation_id": "RC_187"
        },
        {
            "decision": "that you take your medications on time",
            "category": "Category 5: Drug related",
            "start_offset": 14974,
            "end_offset": 15012,
            "annotation_id": "RC_188"
        },
        {
            "decision": ", and that you follow-up with your providers as recommended below.",
            "category": "Category 9: Advice and precaution",
            "start_offset": 15014,
            "end_offset": 15077,
            "annotation_id": "RC_189"
        },
        {
            "decision": "-we scheduled an appointment with Dr. [**Last Name (STitle) **] for Friday [**4-24**] at 11:15. It is very important that you go to this appointment for blood pressure check and blood tests. Her office phone is [**Telephone/Fax (1) 66039**].",
            "category": "Category 1: Contact related",
            "start_offset": 15147,
            "end_offset": 15387,
            "annotation_id": "RC_190"
        },
        {
            "decision": "-you have an appointment with your therapist Ms. [**First Name8 (NamePattern2) 81589**] [**Last Name (Titles) **] on [**5-7**] at 10AM",
            "category": "Category 1: Contact related",
            "start_offset": 15389,
            "end_offset": 15523,
            "annotation_id": "RC_191"
        },
        {
            "decision": "-you have an appointment in psychopharmacology clinic with Dr. [**First Name8 (NamePattern2) 81590**] [**Last Name (NamePattern1) **] on [**6-5**] at 10AM.",
            "category": "Category 1: Contact related",
            "start_offset": 15525,
            "end_offset": 15679,
            "annotation_id": "RC_192"
        },
        {
            "decision": "-[**First Name11 (Name Pattern1) 312**] [**Last Name (NamePattern4) 3015**], M.D. Phone:[**Telephone/Fax (1) 1803**] Date/Time:[**2144-6-10**] 1:00",
            "category": "Category 1: Contact related",
            "start_offset": 15720,
            "end_offset": 15866,
            "annotation_id": "RC_193"
        },
        {
            "decision": "-[**First Name11 (Name Pattern1) **] [**Last Name (NamePattern4) 3469**], MD Phone:[**Telephone/Fax (1) 1237**] Date/Time:[**2144-5-27**] 2:15",
            "category": "Category 1: Contact related",
            "start_offset": 15868,
            "end_offset": 16009,
            "annotation_id": "RC_194"
        }
    ]
}